setup.py
image2gif/__init__.py
image2gif/image2gif.py
image2gif.egg-info/PKG-INFO
image2gif.egg-info/SOURCES.txt
image2gif.egg-info/dependency_links.txt
image2gif.egg-info/top_level.txt