Metadata-Version: 1.1
Name: image2gif
Version: 1.0.0
Summary: read and write animated gifs,for Pillow
Home-page: https://github.com/lucyking/image2gif
Author: lucyking
Author-email: joehisaishi1943@gmail.com
License: BSD
Keywords: gif images Pillow
Platform: UNKNOWN
Classifier: Development Status :: 3 - Alpha
Classifier: Intended Audience :: Developers
Classifier: Topic :: Software Development :: Build Tools
Classifier: License :: OSI Approved :: BSD License
Classifier: Programming Language :: Python :: 2
Classifier: Programming Language :: Python :: 2.6
Classifier: Programming Language :: Python :: 2.7
Classifier: Programming Language :: Python :: 3
Classifier: Programming Language :: Python :: 3.2
Classifier: Programming Language :: Python :: 3.3
Classifier: Programming Language :: Python :: 3.4
Classifier: Programming Language :: Python :: 3.5
